404.html
MANIFEST.in
README.md
run_tests.py
setup.py
tests_settings.py
tests_urls.py
django_jqueryfileupload.egg-info/PKG-INFO
django_jqueryfileupload.egg-info/SOURCES.txt
django_jqueryfileupload.egg-info/dependency_links.txt
django_jqueryfileupload.egg-info/requires.txt
django_jqueryfileupload.egg-info/top_level.txt
jqueryfileupload/__init__.py
jqueryfileupload/models.py
jqueryfileupload/tests.py
jqueryfileupload/urls.py
jqueryfileupload/views.py