Metadata-Version: 1.1
Name: django-jqueryfileupload
Version: 0.0.1
Summary: Django app for handle multiple file uploads via jquery-file-upload plugin.
Home-page: http://desarrollo.witoi.com/
Author: Pedro Buron, Alejandro Varas
Author-email: pedro@witoi.com, alejandro@witoi.com
License: UNKNOWN
Platform: UNKNOWN
Classifier: Development Status :: 3 - Alpha
Classifier: Environment :: Web Environment
Classifier: Framework :: Django
Classifier: Intended Audience :: Developers
Classifier: License :: OSI Approved :: GNU General Public License v3 (GPLv3)
Classifier: Operating System :: OS Independent
Classifier: Programming Language :: Python
Classifier: Topic :: Utilities
